filetracker/__init__.py
filetracker/utils.py
filetracker/client/__init__.py
filetracker/client/client.py
filetracker/client/data_store.py
filetracker/client/dummy.py
filetracker/client/local_data_store.py
filetracker/client/local_data_store_test.py
filetracker/client/lock_manager.py
filetracker/client/remote_data_store.py
filetracker/client/shell.py
filetracker/scripts/__init__.py
filetracker/scripts/cachecleaner.py
filetracker/scripts/migrate.py
filetracker/scripts/migrate_test.py
filetracker/scripts/progress_bar.py
filetracker/scripts/recover.py
filetracker/scripts/recover_test.py
filetracker/servers/__init__.py
filetracker/servers/base.py
filetracker/servers/files.py
filetracker/servers/migration.py
filetracker/servers/run.py
filetracker/servers/storage.py
filetracker/servers/storage_test.py
filetracker/tests/__init__.py
filetracker/tests/interaction_test.py
filetracker/tests/migration_test.py
filetracker/tests/parallel_test.py
filetracker/tests/protocol_test.py
filetracker-2.2.0.dist-info/LICENSE
filetracker-2.2.0.dist-info/METADATA
filetracker-2.2.0.dist-info/WHEEL
filetracker-2.2.0.dist-info/entry_points.txt
filetracker-2.2.0.dist-info/top_level.txt
filetracker-2.2.0.dist-info/RECORD
