Metadata-Version: 2.1
Name: filetracker
Version: 2.2.0
Summary: Filetracker caching file storage
Author-email: SIO2 Project Team <sio2@sio2project.mimuw.edu.pl>
License: GPL
Project-URL: homepage, https://github.com/sio2project/filetracker
Classifier: Framework :: Django
Classifier: Programming Language :: Python :: 3
Requires-Python: >=3.7
License-File: LICENSE
Requires-Dist: bsddb3 ==6.2.7
Requires-Dist: flup6
Requires-Dist: gunicorn ==19.9.0
Requires-Dist: progressbar2
Requires-Dist: requests
Requires-Dist: six
Provides-Extra: server
Requires-Dist: gevent ==22.10.2 ; extra == 'server'
Requires-Dist: greenlet ==2.0.2 ; extra == 'server'
Provides-Extra: tests
Requires-Dist: pytest ; extra == 'tests'
